{
    "pre_AUTH": {
        "userName": "nuts",
        "AuthInfo": {
            "CHAP-Password": "0xbbfb7294c457d60b003d0ac4b063654eea",
            "NAS-IP-Address": "127.0.0.1",
            "NAS-Port": "0",
            "Message-Authenticator": "0x269552f04df9a4b1a2c8e1200a385023"
        }
    },
    "AUTH": {
        "[preprocess]": "ok",
        "[chap]": "ok",
        "[files]": "ok"
    },
    "post_AUTH": {
        "[chap]": "ok",
        "Auth": "Login OK: [nuts/<CHAP-Password>] (from client localhost port 0)"
    }
}