{
    "pre_AUTH": {
        "userName": "nuts",
        "AuthInfo": {
            "NAS-IP-Address": "127.0.0.1",
            "NAS-Port": "0",
            "Message-Authenticator": "0xfbcf3b204162f2859bd5884599009351",
            "MS-CHAP-Challenge": "0x146fd2ce3b9a3ee7",
            "MS-CHAP-Response": "0x000100000000000000000000000000000000000000000000000022245c3354d2db1d8effa461b49f1efded8edbe325a4e0c2"
        }
    },
    "AUTH": {
        "[preprocess]": "ok",
        "[mschap]": "ok",
        "[files]": "ok"
    },
    "post_AUTH": {
        "[attr_filter.access_reject]": "updated",
        "Auth": "Login incorrect (mschap: MS-CHAP2-Response is incorrect): [nuts/<via Auth-Type = mschap>] (from client localhost port 0)"
    }
}